docs/Makefile
docs/conf.py
docs/index.rst
docs/make.bat
docs/rtd-pip-requirements
examples/README.txt
examples/plot_basic.py
licenses/LICENSE.rst
licenses/README.rst
licenses/TEMPLATE_LICENSE.rst
powspec/__init__.py
powspec/_version.py
powspec/powspec.py
powspec/version.py
powspec/data/README.rst
powspec/example_subpkg/__init__.py
powspec/example_subpkg/data/.gitignore
powspec/example_subpkg/tests/__init__.py
powspec/tests/__init__.py
powspec/tests/test_powspec.py
powspec/utils/__init__.py
powspec/utils/apod.py
powspec/utils/generator.py
powspec/utils/tests/__init__.py
powspec/utils/tests/test_apod.py
powspec/utils/tests/test_generator.py
powspec-0.3.dist-info/METADATA
powspec-0.3.dist-info/WHEEL
powspec-0.3.dist-info/entry_points.txt
powspec-0.3.dist-info/top_level.txt
powspec-0.3.dist-info/RECORD
