Metadata-Version: 2.1
Name: powspec
Version: 0.3
Summary: Auto and Cross Spectral Density Estimator
Author-email: "Alexandre Beelen, Mathilde Van Cuyck" <alexandre.beelen@lam.fr>
License: Copyright (c) 2023, Alexandre Beelen, Mathilde Van Cuyck
Project-URL: repository, https://powspec.readthedocs.io
Requires-Python: >=3.9
Provides-Extra: docs
Requires-Dist: sphinx ; extra == 'docs'
Requires-Dist: sphinx-automodapi ; extra == 'docs'
Requires-Dist: sphinx-gallery ; extra == 'docs'
Requires-Dist: tomli ; (python_version < "3.11") and extra == 'docs'
Provides-Extra: test
Requires-Dist: pytest ; extra == 'test'
Requires-Dist: pytest-doctestplus ; extra == 'test'
